ivp_automation/__init__.py
ivp_automation/agama/__init__.py
ivp_automation/agama/api.py
ivp_automation/cms/__init__.py
ivp_automation/cms/api.py
ivp_automation-0.1.0.dist-info/METADATA
ivp_automation-0.1.0.dist-info/WHEEL
ivp_automation-0.1.0.dist-info/RECORD
