Metadata-Version: 2.1
Name: ivp-automation
Version: 0.1.0
Summary: IVP Analytics Automation
Author: Apsar Shaik
Author-email: shaik.apsar@hotmail.com
Requires-Python: >=3.7,<4.0
Classifier: Programming Language :: Python :: 3
Classifier: Programming Language :: Python :: 3.7
Classifier: Programming Language :: Python :: 3.8
Classifier: Programming Language :: Python :: 3.9
Classifier: Programming Language :: Python :: 3.10
Classifier: Programming Language :: Python :: 3.11
Requires-Dist: bs4 (>=0.0.1,<0.0.2)
Requires-Dist: requests (>=2.31.0,<3.0.0)
